LICENSE
README.md
graphiql_strawberry_debug_toolbar/__init__.py
graphiql_strawberry_debug_toolbar/middleware.py
graphiql_strawberry_debug_toolbar/serializers.py
graphiql_strawberry_debug_toolbar/static/graphiql_strawberry_debug_toolbar/js/parse.js
graphiql_strawberry_debug_toolbar/templates/graphiql_strawberry_debug_toolbar/base.html
django_graphiql_strawberry_debug_toolbar-0.2.0.dist-info/LICENSE
django_graphiql_strawberry_debug_toolbar-0.2.0.dist-info/WHEEL
django_graphiql_strawberry_debug_toolbar-0.2.0.dist-info/METADATA
django_graphiql_strawberry_debug_toolbar-0.2.0.dist-info/RECORD
