Metadata-Version: 2.1
Name: django-graphiql-strawberry-debug-toolbar
Version: 0.2.0
Summary: Django Debug Toolbar for GraphiQL IDE in Strawberry.
Home-page: https://github.com/przemub/django-graphiql-strawberry-debug-toolbar
License: MIT
Keywords: django,graphql,graphiql,debug,strawberry
Author: mongkok
Author-email: dani@domake.io
Requires-Python: >=3.7,<4.0
Classifier: Development Status :: 4 - Beta
Classifier: Environment :: Web Environment
Classifier: Framework :: Django
Classifier: Framework :: Django :: 2.2
Classifier: Framework :: Django :: 3.0
Classifier: Framework :: Django :: 3.1
Classifier: Framework :: Django :: 3.2
Classifier: Intended Audience :: Developers
Classifier: Intended Audience :: Information Technology
Classifier: Intended Audience :: System Administrators
Classifier: License :: OSI Approved :: MIT License
Classifier: Operating System :: OS Independent
Classifier: Programming Language :: Python
Classifier: Programming Language :: Python :: 3
Classifier: Programming Language :: Python :: 3.10
Classifier: Programming Language :: Python :: 3.7
Classifier: Programming Language :: Python :: 3.8
Classifier: Programming Language :: Python :: 3.9
Classifier: Topic :: Internet
Classifier: Topic :: Internet :: WWW/HTTP
Classifier: Topic :: Internet :: WWW/HTTP :: HTTP Servers
Classifier: Topic :: Software Development
Classifier: Topic :: Software Development :: Debuggers
Classifier: Topic :: Software Development :: Libraries
Classifier: Topic :: Software Development :: Libraries :: Python Modules
Classifier: Topic :: Utilities
Requires-Dist: Django (>=2.2)
Requires-Dist: django-debug-toolbar (>=3.1)
Requires-Dist: strawberry-graphql (>=0.15.1)
Project-URL: Repository, https://github.com/przemub/django-graphiql-strawberry-debug-toolbar
